{
  "name": "Ricky Blake",
  "age": 27,
  "address": {
    "street": "Cipo Court",
    "city": "Fozzemfat",
    "state": "AL",
    "zip": "05660"
  },
  "contact": {
    "phone": "(647) 638-2423",
    "servicePhone": "800521434"
  },
  "birthday": "1994-04-05T00:07:16.253Z",
  "ip": "211.186.41.208",
  "foo": "bar",
  "profile": {
    "about": "Weganumu hipkukok pag tape wolokusi or bakdeuwa wev lumwuva zovwo cuku wifolavul awi tohi galbe wipazu peomi wulaub. Tikwensov gulsorvez dovul sa isbi wiafseg muw puru no la se bukninwoz gejkot. Ri mujnokha seha fevacve ad um jaodaha geluro poatneg up oraiwda juka ili. Mobugur ra bizi uz ja itouh ruccum nigcim wabcussi hod amukvi wo. Funrerseh wivnumot eztaabi piwivha ufiiv an neci pefka mu fapo ressov uwinen uziri pe ac patorpot. Taldot lefkikji johu amo biazsu dop cugap winbew low juridgu sazwiwta luknujuze ojudook opuzimi zolbo.",
    "bio": "Tod ko kar hojiaku po umoup vitbi ukutilje nagofe adwun ibbetjid nu ziccu del aj. Savazi eplibwod uriterpu ajokokiz daisekap jugkehso obmev vikujzu uc jo zug omupu donaad baded ti tuduh okpud. Tithuja koroceg pergirnus giehuuf uw otlopmo cu najabo liv delbag gu nojrun nufpilpic deacuced. Cewfop geoso ajagauki te pe varowpak suw weew rumuwog fi nusu sed hagew sogoczol opve jur seru ewoiffi. Mezhe taaleja tic fibari kac weri badifo raikevi fe buz sukub hid gomuzuj bu."
  },
  "apiKey": "0352e0811399af3f943d7fd000f2f28ecffcd73dd37de1f736ec77b7e158bfa2",
  "currency": {
    "code": "BZD",
    "name": "Belize Dollar"
  }
}