{
  "name": "Olivia Banks",
  "age": 23,
  "address": {
    "street": "Cuuju Drive",
    "city": "Dusekusi",
    "state": "AK",
    "zip": "57351"
  },
  "contact": {
    "phone": "(668) 280-4121",
    "servicePhone": "800574963"
  },
  "birthday": "1983-12-25T11:33:35.917Z",
  "ip": "114.21.41.234",
  "foo": "bar",
  "profile": {
    "about": "Matev vakevel su gu pal demim apiza gi vu votfi sem segoba opopiguj jor. Nohogna mihtop mougetul foesa ig sosa lupabilu iruegeeb poppupob ugu lampaof ermig gi. Ti oji suedo acsi publu zeufiluw zihugfe magu doeh ok aca cohuboci woikvu cem ca zoh anide guf.",
    "bio": "Ludkura raitede pijac ekfusa ucuazimot se johog des na ule obde do. Ruwesu agote irateav ge tifuk alidowe lu rofdu josi vo nutzab afnueri vivocoju juzeple faznuwil huikepig. Lama efetiwu cof of megfudgu zezihwi tar ucotubsu pa pad pe camaje oresisok ob. Sejber wavcuf gurukobi vic eddebre mezuv nosreoji icofe be raw unjupki zefeseteh ge da deg ejda wut mud. Wiase iko geweet vi enjeh awe cijve da vidahde seabo konses lizvupu movoj deapini zop tulnu akawag bo."
  },
  "apiKey": "6642693acfdb94a256dc5f69cf3ebb8211140df0ac210d2914f5a57a24dd8d6d",
  "currency": {
    "code": "IRR",
    "name": "Iran Rial"
  }
}