{
  "name": "Ellen McCarthy",
  "age": 52,
  "address": {
    "street": "Gelwul Avenue",
    "city": "Ihuapugu",
    "state": "DE",
    "zip": "10303"
  },
  "contact": {
    "phone": "(317) 533-1509",
    "servicePhone": "800287129"
  },
  "birthday": "1967-12-03T04:31:43.532Z",
  "ip": "181.232.172.76",
  "foo": "bar",
  "profile": {
    "about": "Vikonve huvma hi owfu lehnamne jiraf idicodti laid sicib boepo rog afu rencir ocasu cikta. Lejjolfe hegaeju vucmi cozit mu ihiko zisdipnu uvtolrin hebderepa wo vowekdic evaho dob teeg. Vaznemop no buiruvet hinjo coiv utijetrac goeh bu nahwi koot cewoh doh. Cakot vim nafrepos caf rotu vo wip fetaswe mu talebdoz epdit kasojuod hac. Fikjeg sietwe ripulo na ku zuji sode beda odukemaw donavza apwohor cekga agade vuw lolufi rusu hapajpub ju. Tiffouno nolubi arfad sa sopfoen viis lerdum iztu kosnu uro ehri refuk vukis ralakgun geste iv.",
    "bio": "Wef gir iknil li koljevip ege wok sa uni atus ka nedib akse zucev. Mehelwu wemoptar ufauj ru ef alcat volraoda ap cusi igtet farnu tulzig gubihaz kofla lihemga log di. Uddaco bap mar oto zewonoju ji cej pegva loldik gag malorew nogjisuto ci."
  },
  "apiKey": "8122f8fa5c462939d92c103e1cfcd135bf16ed34356d4b3fb832131ada9a8956",
  "currency": {
    "code": "TOP",
    "name": "Tonga Pa'anga"
  }
}